{"original": {"decision": {"no-options": [{"accuracy-perc": 1.0, "error-perc": 0.0, "mean-error": 0.0, "error-std": 0.0, "total-correct": 324, "total-incorrect": 0, "min-error": 0, "max-error": 0, "error-counts": {"k0": 324}}, {"accuracy-perc": 1.0, "error-perc": 0.0, "mean-error": 0.0, "error-std": 0.0, "total-correct": 6173, "total-incorrect": 0, "min-error": 0, "max-error": 0, "error-counts": {"k0": 6173}}], "with-options": [{"accuracy-perc": 0.9969135802469136, "error-perc": 0.0030864197530864335, "mean-error": 0.0030864197530864196, "error-std": 0.05546975541855344, "total-correct": 323, "total-incorrect": 1, "min-error": 0, "max-error": 1, "error-counts": {"k0": 323, "k1": 1}}, {"accuracy-perc": 0.9953021221448243, "error-perc": 0.004697877855175725, "mean-error": 0.004697877855175766, "error-std": 0.06837987861084494, "total-correct": 6144, "total-incorrect": 29, "min-error": 0, "max-error": 1, "error-counts": {"k0": 6144, "k1": 29}}]}, "ada": {"no-options": [{"accuracy-perc": 1.0, "error-perc": 0.0, "mean-error": 0.0, "error-std": 0.0, "total-correct": 324, "total-incorrect": 0, "min-error": 0, "max-error": 0, "error-counts": {"k0": 324}}, {"accuracy-perc": 1.0, "error-perc": 0.0, "mean-error": 0.0, "error-std": 0.0, "total-correct": 6173, "total-incorrect": 0, "min-error": 0, "max-error": 0, "error-counts": {"k0": 6173}}], "with-options": [{"accuracy-perc": 1.0, "error-perc": 0.0, "mean-error": 0.0, "error-std": 0.0, "total-correct": 324, "total-incorrect": 0, "min-error": 0, "max-error": 0, "error-counts": {"k0": 324}}, {"accuracy-perc": 1.0, "error-perc": 0.0, "mean-error": 0.0, "error-std": 0.0, "total-correct": 6173, "total-incorrect": 0, "min-error": 0, "max-error": 0, "error-counts": {"k0": 6173}}]}}}